{
	"info": {
		"_postman_id": "5b08f7ac-71d0-4927-92a4-7d334cfcf7d8",
		"name": "CollectionRestaurantes",
		"schema": "https://schema.getpostman.com/json/collection/v2.1.0/collection.json",
		"_exporter_id": "43766248"
	},
	"item": [
		{
			"name": "restaurante",
			"item": [
				{
					"name": "ObtenerTodos",
					"request": {
						"method": "GET",
						"header": [],
						"url": {
							"raw": "http://localhost:3000/restaurantes",
							"protocol": "http",
							"host": [
								"localhost"
							],
							"port": "3000",
							"path": [
								"restaurantes"
							]
						}
					},
					"response": []
				},
				{
					"name": "SubirUno",
					"request": {
						"method": "POST",
						"header": [],
						"body": {
							"mode": "raw",
							"raw": "{\r\n    \"id_rest\":\"55\",\r\n    \"nombre\": \"Restaurante x\",\r\n    \"ciudad\": \"Ciudad A\",\r\n    \"direccion\": \"Dirección dbca\",\r\n    \"fecha_apertura\": \"2024-07-28\"\r\n}",
							"options": {
								"raw": {
									"language": "json"
								}
							}
						},
						"url": {
							"raw": "http://localhost:3000/restaurantes",
							"protocol": "http",
							"host": [
								"localhost"
							],
							"port": "3000",
							"path": [
								"restaurantes"
							]
						}
					},
					"response": []
				},
				{
					"name": "consultaId",
					"request": {
						"method": "GET",
						"header": [],
						"url": {
							"raw": "http://localhost:3000/restaurantes/5",
							"protocol": "http",
							"host": [
								"localhost"
							],
							"port": "3000",
							"path": [
								"restaurantes",
								"5"
							]
						}
					},
					"response": []
				},
				{
					"name": "Actualizar",
					"request": {
						"method": "PUT",
						"header": [],
						"body": {
							"mode": "raw",
							"raw": "{\r\n    \"nombre\": \"super Burger Heaven\",\r\n    \"ciudad\": \"New new York\",\r\n    \"direccion\": \"123 Main St \",\r\n    \"fecha_apertura\": \"2023-06-10\"\r\n}",
							"options": {
								"raw": {
									"language": "json"
								}
							}
						},
						"url": {
							"raw": "http://localhost:3000/restaurantes/33",
							"protocol": "http",
							"host": [
								"localhost"
							],
							"port": "3000",
							"path": [
								"restaurantes",
								"33"
							]
						}
					},
					"response": []
				},
				{
					"name": "Delete",
					"request": {
						"method": "DELETE",
						"header": [],
						"url": {
							"raw": "http://localhost:3000/restaurantes/1",
							"protocol": "http",
							"host": [
								"localhost"
							],
							"port": "3000",
							"path": [
								"restaurantes",
								"1"
							]
						}
					},
					"response": []
				}
			]
		},
		{
			"name": "Producto",
			"item": [
				{
					"name": "ObtenerProductos",
					"request": {
						"method": "GET",
						"header": [],
						"url": {
							"raw": "http://localhost:3000/productos",
							"protocol": "http",
							"host": [
								"localhost"
							],
							"port": "3000",
							"path": [
								"productos"
							]
						}
					},
					"response": []
				},
				{
					"name": "SubirUno",
					"request": {
						"method": "POST",
						"header": [],
						"body": {
							"mode": "raw",
							"raw": "{\r\n    \"nombre\": \"Producto CI\",\r\n    \"precio\": 140.25\r\n}",
							"options": {
								"raw": {
									"language": "json"
								}
							}
						},
						"url": {
							"raw": "http://localhost:3000/productos",
							"protocol": "http",
							"host": [
								"localhost"
							],
							"port": "3000",
							"path": [
								"productos"
							]
						}
					},
					"response": []
				},
				{
					"name": "Consultad",
					"request": {
						"method": "GET",
						"header": [],
						"url": {
							"raw": "http://localhost:3000/productos/44",
							"protocol": "http",
							"host": [
								"localhost"
							],
							"port": "3000",
							"path": [
								"productos",
								"44"
							]
						}
					},
					"response": []
				},
				{
					"name": "Actualizar",
					"request": {
						"method": "PUT",
						"header": [],
						"body": {
							"mode": "raw",
							"raw": "{\r\n    \"nombre\": \"Classic Burger Updated\",\r\n    \"precio\": 9.99\r\n}",
							"options": {
								"raw": {
									"language": "json"
								}
							}
						},
						"url": {
							"raw": "http://localhost:3000/productos/44",
							"protocol": "http",
							"host": [
								"localhost"
							],
							"port": "3000",
							"path": [
								"productos",
								"44"
							]
						}
					},
					"response": []
				},
				{
					"name": "Delete",
					"request": {
						"method": "DELETE",
						"header": [],
						"url": {
							"raw": "http://localhost:3000/productos/51",
							"protocol": "http",
							"host": [
								"localhost"
							],
							"port": "3000",
							"path": [
								"productos",
								"51"
							]
						}
					},
					"response": []
				}
			]
		},
		{
			"name": "Empleado",
			"item": [
				{
					"name": "ObtenerEmpleado",
					"request": {
						"method": "GET",
						"header": []
					},
					"response": []
				},
				{
					"name": "SubirUno",
					"request": {
						"method": "POST",
						"header": []
					},
					"response": []
				},
				{
					"name": "consultaid",
					"request": {
						"method": "GET",
						"header": []
					},
					"response": []
				},
				{
					"name": "actualizar",
					"request": {
						"method": "PUT",
						"header": []
					},
					"response": []
				},
				{
					"name": "eliminar",
					"request": {
						"method": "DELETE",
						"header": []
					},
					"response": []
				}
			]
		},
		{
			"name": "Pedidos",
			"item": [
				{
					"name": "ObtenerPedidos",
					"request": {
						"method": "GET",
						"header": []
					},
					"response": []
				},
				{
					"name": "SubirUno",
					"request": {
						"method": "POST",
						"header": []
					},
					"response": []
				},
				{
					"name": "ConsultaId",
					"request": {
						"method": "GET",
						"header": []
					},
					"response": []
				},
				{
					"name": "actualizar",
					"request": {
						"method": "GET",
						"header": []
					},
					"response": []
				},
				{
					"name": "eliminar",
					"request": {
						"method": "DELETE",
						"header": []
					},
					"response": []
				}
			]
		},
		{
			"name": "DetallePedido",
			"item": [
				{
					"name": "ObtenerDetalle",
					"request": {
						"method": "GET",
						"header": [],
						"url": {
							"raw": "http://localhost:3000/detalles-pedido",
							"protocol": "http",
							"host": [
								"localhost"
							],
							"port": "3000",
							"path": [
								"detalles-pedido"
							]
						}
					},
					"response": []
				},
				{
					"name": "SubirUno",
					"request": {
						"method": "POST",
						"header": []
					},
					"response": []
				},
				{
					"name": "ConsultaId",
					"request": {
						"method": "GET",
						"header": []
					},
					"response": []
				},
				{
					"name": "Actualizar",
					"request": {
						"method": "PUT",
						"header": []
					},
					"response": []
				},
				{
					"name": "Eliminar",
					"request": {
						"method": "DELETE",
						"header": [],
						"url": {
							"raw": "http://localhost:3000/detalles-pedido/22",
							"protocol": "http",
							"host": [
								"localhost"
							],
							"port": "3000",
							"path": [
								"detalles-pedido",
								"22"
							]
						}
					},
					"response": []
				}
			]
		},
		{
			"name": "Consultas",
			"item": [
				{
					"name": "1ProductosDePedido",
					"request": {
						"method": "GET",
						"header": [],
						"url": {
							"raw": "http://localhost:3000/pedidos/10/productos",
							"protocol": "http",
							"host": [
								"localhost"
							],
							"port": "3000",
							"path": [
								"pedidos",
								"10",
								"productos"
							]
						}
					},
					"response": []
				},
				{
					"name": "2MasVendiddos",
					"request": {
						"method": "GET",
						"header": [],
						"url": {
							"raw": "http://localhost:3000/productos/mas-vendidos/8",
							"protocol": "http",
							"host": [
								"localhost"
							],
							"port": "3000",
							"path": [
								"productos",
								"mas-vendidos",
								"8"
							]
						}
					},
					"response": []
				},
				{
					"name": "3RestaurantesVentas",
					"request": {
						"method": "GET",
						"header": [],
						"url": {
							"raw": "http://localhost:3000/restaurante/ventas",
							"protocol": "http",
							"host": [
								"localhost"
							],
							"port": "3000",
							"path": [
								"restaurante",
								"ventas"
							]
						}
					},
					"response": []
				},
				{
					"name": "4RestauranteFecha",
					"request": {
						"method": "GET",
						"header": [],
						"url": {
							"raw": "http://localhost:3000/restaurante/ventas",
							"protocol": "http",
							"host": [
								"localhost"
							],
							"port": "3000",
							"path": [
								"restaurante",
								"ventas"
							]
						}
					},
					"response": []
				},
				{
					"name": "5empleadoRol",
					"request": {
						"method": "GET",
						"header": [],
						"url": {
							"raw": "http://localhost:3000/restaurantes/10/empleados/limpieza",
							"protocol": "http",
							"host": [
								"localhost"
							],
							"port": "3000",
							"path": [
								"restaurantes",
								"10",
								"empleados",
								"limpieza"
							]
						}
					},
					"response": []
				}
			]
		}
	]
}